sphinxcontrib_trio/__init__.py
sphinxcontrib_trio/_version.py
sphinxcontrib_trio-1.1.1.dist-info/LICENSE
sphinxcontrib_trio-1.1.1.dist-info/LICENSE.APACHE2
sphinxcontrib_trio-1.1.1.dist-info/LICENSE.MIT
sphinxcontrib_trio-1.1.1.dist-info/METADATA
sphinxcontrib_trio-1.1.1.dist-info/WHEEL
sphinxcontrib_trio-1.1.1.dist-info/top_level.txt
sphinxcontrib_trio-1.1.1.dist-info/RECORD
