Metadata-Version: 2.1
Name: sphinxcontrib-trio
Version: 1.1.1
Summary: Make Sphinx better at documenting Python functions and methods
Home-page: https://github.com/python-trio/sphinxcontrib-trio
Author: Nathaniel J. Smith
Author-email: njs@pobox.com
License: MIT -or- Apache License 2.0
Platform: UNKNOWN
Classifier: Development Status :: 5 - Production/Stable
Classifier: Intended Audience :: Developers
Classifier: License :: OSI Approved :: MIT License
Classifier: License :: OSI Approved :: Apache Software License
Classifier: Programming Language :: Python :: 3
Classifier: Programming Language :: Python :: 3.5
Classifier: Programming Language :: Python :: 3.6
Classifier: Framework :: Sphinx :: Extension
Classifier: Framework :: Trio
Classifier: Framework :: AsyncIO
Classifier: Framework :: Twisted
Classifier: Topic :: Documentation :: Sphinx
Classifier: Topic :: Software Development :: Documentation
Requires-Dist: sphinx (>=1.7)
